setup.py
arwa_distributions_probability_mle/Binomialdistribution.py
arwa_distributions_probability_mle/Gaussiandistribution.py
arwa_distributions_probability_mle/Generaldistribution.py
arwa_distributions_probability_mle/__init__.py
arwa_distributions_probability_mle.egg-info/PKG-INFO
arwa_distributions_probability_mle.egg-info/SOURCES.txt
arwa_distributions_probability_mle.egg-info/dependency_links.txt
arwa_distributions_probability_mle.egg-info/not-zip-safe
arwa_distributions_probability_mle.egg-info/top_level.txt