Metadata-Version: 1.0
Name: arwa-distributions-probability-mle
Version: 1.1
Summary: Gaussian distributions
Home-page: UNKNOWN
Author: UNKNOWN
Author-email: UNKNOWN
License: UNKNOWN
Platform: UNKNOWN
